{"name":"ESEMSA","tagline":"Elettroacustica e Sistemi Elettroacustici - Master Sonic Arts","body":"#Elettroacustica e sistemi elettroacustici\r\n###Master Sonic Arts\r\n\r\n1. Introduzione alle diverse tipologie di microfoni, per architettura, per curve polari e per utilizzo.\r\n\t- Architettura e principio di funzionamento\r\n\t- Curve polari\r\n\t- Utilizzo\r\n\t- Posizionamento panoramico\r\n\t- Posizionamento individuale\r\n\t- Il microfono su alcuni strumenti\r\n\r\n2. Le coppie stereofoniche\r\n\t- Parametri di valutazione della ripresa stereofonica\r\n\t\t- localizzazione\r\n\t\t- definizione timbrica\r\n\t\t- profondità\r\n\t\t- spaziosità\r\n\t- Tipologie di coppie stereofoniche\r\n\t\t- coppie coincidenti\r\n\t\t- coppie quasi-coincidenti\r\n\t\t- coppie spaziate\r\n\t- La percezione della direzionalità del suono\r\n\t- Differenza di tempo\r\n\t- Differenza di intensità\t\r\n\r\n3. Lezione laboratorio sulle coppie stereofoniche.\r\n\r\n4. La consolle di missaggio nelle sue architetture e nelle tipologie di utilizzo.\r\n\t- Tipologie di utilizzo\r\n\t- Connessioni\r\n\t- Livelli\r\n\t- Architettura del mixer\r\n\r\n5. Introduzione ai sistemi di amplificazione. Diffusione e monitoraggio.\r\n\t- La catena di amplificazione\r\n\t- Gli amplificatori\r\n\t- Gli altoparlanti\r\n\t- Le casse acustiche\r\n\t- I crossover\r\n\t- Diffusione orizzontale e verticale\r\n\r\n6. Oltre la stereofonia: tecnologie multicanale per la spazializzazione\r\n\t- Il cono di confusione e le HRTF\r\n\t- I primi esperimenti \r\n\t- Il Dolby Surround\r\n\t- Il Surround 5.1 e oltre\r\n\t- Cenni storici e configurazioni: la spazializzazione audio\r\n\t- La quadrifonia\r\n\t- Ambisonics\r\n\t- Phantom images\r\n\t- Percezione timbrica e localizzazione\r\n\r\n###Testi\r\nDispense a cura del docente.","google":"UA-49989534-2","note":"Don't delete this file! It's used internally to help with page regeneration."}